prompt_peel/__init__.py
prompt_peel/dsl.py
prompt_peel/exceptions.py
prompt_peel/format.py
prompt_peel/lib.py
prompt_peel/message.py
prompt_peel/node.py
prompt_peel/token_counter.py
prompt_peel-0.1.0.dist-info/METADATA
prompt_peel-0.1.0.dist-info/WHEEL
prompt_peel-0.1.0.dist-info/RECORD
