Metadata-Version: 2.1
Name: prompt_peel
Version: 0.1.0
Summary: 
Author: asim-shrestha
Author-email: asim.shrestha@hotmail.com
Requires-Python: >=3.11,<4.0
Classifier: Programming Language :: Python :: 3
Classifier: Programming Language :: Python :: 3.11
Classifier: Programming Language :: Python :: 3.12
Requires-Dist: tiktoken (>=0.5.2,<0.6.0)
